{
    "hdf_audio_codec_primary_dev0": [
        {
            "deep-buffer-playback": [
                {
                    "headphones": [
                        {
                            "name": "Playback Path",
                            "value": "2"
                        }
                    ],
                    "Speaker": [
                        {
                            "name": "agdsp_access_en",
                            "value": "1"
                        },
                        {
                            "name": "agdsp_access_a2dp_en",
                            "value": "1"
                        },
                        {
                            "name": "DAC LRCLK Select",
                            "value": "1"
                        },
                        {
                            "name": "HPL Mixer DACLHPL Switch",
                            "value": "1"
                        },
                        {
                            "name": "HPR Mixer DACRHPR Switch",
                            "value": "1"
                        },
                        {
                            "name": "HPL EAR Sel",
                            "value": "1"
                        },
                        {
                            "name": "HP Virt Switch",
                            "value": "1"
                        },
                        {
                            "name": "Speaker Function",
                            "value": "1"
                        },
                        {
                            "name": "Speaker1 Function",
                            "value": "1"
                        },
                        {
                            "name": "ag_iis0_ext_sel_v2",
                            "value": "1"
                        },
                        {
                            "name": "S_NORMAL_AP01_P_CODEC SWITCH",
                            "value": "1"
                        },
                        {
                            "name": "S_NORMAL_AP23_P_CODEC SWITCH",
                            "value": "1"
                        },
                        {
                            "name": "S_FAST_P_CODEC SWITCH",
                            "value": "1"
                        },
                        {
                            "name": "S_OFFLOAD_CODEC SWITCH",
                            "value": "1"
                        },
                        {
                            "name": "S_VOICE_P_CODEC SWITCH",
                            "value": "1"
                        },
                        {
                            "name": "S_VOIP_P_CODEC SWITCH",
                            "value": "1"
                        },
                        {
                            "name": "S_FM_CODEC SWITCH",
                            "value": "1"
                        },
                        {
                            "name": "S_LOOP_P_CODEC SWITCH",
                            "value": "1"
                        },
                        {
                            "name": "S_FM_DSP_CODEC SWITCH",
                            "value": "1"
                        },
                        {
                            "name": "S_VOICE_PCM_P SWITCH",
                            "value": "1"
                        },
                        {
                            "name": "S_FAST_P_SMART_AMP SWITCH",
                            "value": "1"
                        },
                        {
                            "name": "VBC_IIS_TX0_WD_SEL",
                            "value": "1"
                        },
                        {
                            "name": "VBC_IIS_TX1_WD_SEL",
                            "value": "1"
                        },
                        {
                            "name": "VBC_IIS_TX0_LRMOD_SEL",
                            "value": "1"
                        },
                        {
                            "name": "VBC_MUX_DAC0_IIS_PORT_SEL",
                            "value": "0"
                        },
                        {
                            "name": "VBC_MUX_DAC1_IIS_PORT_SEL",
                            "value": "0"
                        },
                        {
                            "name": "VBC_MUX_IIS0_PORT_DO_SEL",
                            "value": "0"
                        },
                        {
                            "name": "VBC_MUX_IIS2_PORT_DO_SEL",
                            "value": "2"
                        },
                        {
                            "name": "VBC_MUX_IIS3_PORT_DO_SEL",
                            "value": "2"
                        },
                        {
                            "name": "VBC DAC0 DG Set",
                            "value": "27 27"
                        },
                        {
                            "name": "DAC Gain DAC Playback Volume",
                            "value": "3"
                        },
                        {
                            "name": "HPL Gain HPL Playback Volume",
                            "value": "0"
                        },
                        {
                            "name": "HPR Gain HPR Playback Volume",
                            "value": "0"
                        }
                    ],
                    "Mic": [
                        {
                            "name": "agdsp_access_en",
                            "value": "1"
                        },
                        {
                            "name": "agdsp_access_a2dp_en",
                            "value": "1"
                        },
                        {
                            "name": "VBC ADC0 DG Set",
                            "value": "24 24"
                        },
                        {
                            "name": "VBC_MUX_ADC1_IIS_PORT_SEL",
                            "value": "2"
                        },
                        {
                            "name": "VBC_IIS_RX2_WD_SEL",
                            "value": "1"
                        },
                        {
                            "name": "ag_iis1_ext_sel_v2",
                            "value": "1"
                        },
                        {
                            "name": "ADC LRCLK Select",
                            "value": "1"
                        },
                        {
                            "name": "ADC1 LRCLK Select",
                            "value": "1"
                        },
                        {
                            "name": "ADD0 DATA SEL",
                            "value": "2"
                        },
                        {
                            "name": "Mic Function",
                            "value": "1"
                        },
                        {
                            "name": "S_NORMAL_AP01_C_CODEC SWITCH",
                            "value": "1"
                        },
                        {
                            "name": "S_NORMAL_AP23_C_CODEC SWITCH",
                            "value": "1"
                        },
                        {
                            "name": "S_CAPTURE_DSP_CODEC SWITCH",
                            "value": "1"
                        },
                        {
                            "name": "S_VOICE_C_CODEC SWITCH",
                            "value": "1"
                        },
                        {
                            "name": "S_VOIP_C_CODEC SWITCH",
                            "value": "1"
                        },
                        {
                            "name": "S_LOOP_C_CODEC SWITCH",
                            "value": "1"
                        },
                        {
                            "name": "ADC_1 Mixer MIC1PGA_1 Switch",
                            "value": "1"
                        },
                        {
                            "name": "AUD ADC0L Switch",
                            "value": "1"
                        },
                        {
                            "name": "AUD ADC0R Switch",
                            "value": "1"
                        },
                        {
                            "name": "ADC_1 Gain ADC_1 Capture Volume",
                            "value": "6"
                        },
                        {
                            "name": "ADC_2 Gain ADC_2 Capture Volume",
                            "value": "6"
                        },
                        {
                            "name": "ADC_3 Gain ADC_3 Capture Volume",
                            "value": "6"
                        }
                    ],
                    "Bluetooth": [
                        {
                            "name": "VBC_IIS_TX0_WD_SEL",
                            "value": "1"
                        },
                        {
                            "name": "VBC_IIS_TX1_WD_SEL",
                            "value": "1"
                        },
                        {
                            "name": "VBC_IIS_MASTER_ENALBE",
                            "value": "0"
                        },
                        {
                            "name": "VBC_IIS_MST_SEL_0_TYPE",
                            "value": "0"
                        },
                        {
                            "name": "VBC_MUX_DAC0_IIS_PORT_SEL",
                            "value": "0"
                        },
                        {
                            "name": "VBC_MUX_DAC1_IIS_PORT_SEL",
                            "value": "0"
                        },
                        {
                            "name": "VBC_MUX_IIS3_PORT_DO_SEL",
                            "value": "2"
                        },
                        {
                            "name": "VBC_MUX_MST_IIS0_PORT_DO_SEL",
                            "value": "0"
                        },
                        {
                            "name": "VBC_MUX_IIS2_PORT_DO_SEL",
                            "value": "2"
                        },
                        {
                            "name": "VBC_MUX_IIS0_PORT_DO_SEL",
                            "value": "0"
                        },
                        {
                            "name": "VBC_IIS_RX0_WD_SEL",
                            "value": "1"
                        },
                        {
                            "name": "VBC_IIS_RX1_WD_SEL",
                            "value": "1"
                        },
                        {
                            "name": "VBC_IIS_RX2_WD_SEL",
                            "value": "1"
                        },
                        {
                            "name": "VBC_MUX_ADC0_IIS_PORT_SEL",
                            "value": "1"
                        },
                        {
                            "name": "VBC_MUX_ADC1_IIS_PORT_SEL",
                            "value": "1"
                        },
                        {
                            "name": "VBC_MUX_ADC2_IIS_PORT_SEL",
                            "value": "1"
                        },
                        {
                            "name": "VBC_MUX_ADC3_IIS_PORT_SEL",
                            "value": "3"
                        },
                        {
                            "name": "VBC_SRC_BT_DAC",
                            "value": "16000"
                        },
                        {
                            "name": "VBC_SRC_BT_ADC",
                            "value": "16000"
                        },
                        {
                            "name": "VBC_VOLUME",
                            "value": "0"
                        },
                        {
                            "name": "ADC_1 Gain ADC_1 Capture Volume",
                            "value": "7"
                        },
                        {
                            "name": "ADC_2 Gain ADC_2 Capture Volume",
                            "value": "7"
                        },
                        {
                            "name": "ADC_3 Gain ADC_3 Capture Volume",
                            "value": "6"
                        },
                        {
                            "name": "DAC Gain DAC Playback Volume",
                            "value": "2"
                        },
                        {
                            "name": "ag_iis2_ext_sel_v2",
                            "value": "0"
                        },
                        {
                            "name": "VBC DAC0 DSP MDG Set",
                            "value": "0 0"
                        },
                        {
                            "name": "VBC DAC1 DSP MDG Set",
                            "value": "0 0"
                        },
                        {
                            "name": "VBC DAC0 AUD MDG Set",
                            "value": "0 0"
                        },
                        {
                            "name": "VBC DAC0 AUD23 MDG Set",
                            "value": "0 0"
                        },
                        {
                            "name": "VBC_UL_MUTE",
                            "value": "0"
                        },
                        {
                            "name": "VBC_DL_MUTE",
                            "value": "0"
                        },
                        {
                            "name": "VBC_IIS_TX0_LRMOD_SEL",
                            "value": "1"
                        },
                        {
                            "name": "VBC_IIS_RX2_LRMOD_SEL",
                            "value": "0"
                        },
                        {
                            "name": "DAC LRCLK Select",
                            "value": "0"
                        },
                        {
                            "name": "ADC LRCLK Select",
                            "value": "1"
                        },
                        {
                            "name": "ADC1 LRCLK Select",
                            "value": "1"
                        },
                        {
                            "name": "S_VOICE_P_BT SWITCH",
                            "value": "0"
                        },
                        {
                            "name": "S_VOIP_P_BT SWITCH",
                            "value": "0"
                        },
                        {
                            "name": "S_LOOP_P_BT SWITCH",
                            "value": "0"
                        },
                        {
                            "name": "S_FAST_P_BT SWITCH",
                            "value": "0"
                        },
                        {
                            "name": "S_NORMAL_AP01_P_BT SWITCH",
                            "value": "0"
                        },
                        {
                            "name": "S_CAPTURE_BT SWITCH",
                            "value": "0"
                        },
                        {
                            "name": "S_VOICE_C_BT SWITCH",
                            "value": "0"
                        },
                        {
                            "name": "S_VOIP_C_BT SWITCH",
                            "value": "0"
                        },
                        {
                            "name": "S_LOOP_C_BT SWITCH",
                            "value": "0"
                        },
                        {
                            "name": "S_BTSCO_CAP_DSP_C SWITCH",
                            "value": "0"
                        },
                        {
                            "name": "agdsp_access_en",
                            "value": "1"
                        },
                        {
                            "name": "agdsp_access_a2dp_en",
                            "value": "1"
                        },
                        {
                            "name": "VBC_IIS_TX0_LRMOD_SEL",
                            "value": "1"
                        },
                        {
                            "name": "VBC_IIS_TX1_WD_SEL",
                            "value": "1"
                        },
                        {
                            "name": "DAC Gain DAC Playback Volume",
                            "value": "2"
                        },
                        {
                            "name": "Speaker Function",
                            "value": "1"
                        },
                        {
                            "name": "S_NORMAL_AP01_P_CODEC SWITCH",
                            "value": "1"
                        },
                        {
                            "name": "S_NORMAL_AP23_P_CODEC SWITCH",
                            "value": "1"
                        },
                        {
                            "name": "S_FAST_P_CODEC SWITCH",
                            "value": "1"
                        },
                        {
                            "name": "S_OFFLOAD_CODEC SWITCH",
                            "value": "1"
                        },
                        {
                            "name": "S_VOICE_P_CODEC SWITCH",
                            "value": "1"
                        },
                        {
                            "name": "S_VOIP_P_CODEC SWITCH",
                            "value": "1"
                        },
                        {
                            "name": "S_FM_CODEC SWITCH",
                            "value": "1"
                        },
                        {
                            "name": "S_LOOP_P_CODEC SWITCH",
                            "value": "1"
                        },
                        {
                            "name": "S_FM_DSP_CODEC SWITCH",
                            "value": "1"
                        },
                        {
                            "name": "S_VOICE_PCM_P SWITCH",
                            "value": "1"
                        },
                        {
                            "name": "S_FAST_P_SMART_AMP SWITCH",
                            "value": "1"
                        },
                        {
                            "name": "VBC_MUX_DAC0_IIS_PORT_SEL",
                            "value": "0"
                        },
                        {
                            "name": "VBC_MUX_DAC1_IIS_PORT_SEL",
                            "value": "0"
                        },
                        {
                            "name": "VBC_MUX_IIS0_PORT_DO_SEL",
                            "value": "0"
                        },
                        {
                            "name": "VBC_MUX_IIS2_PORT_DO_SEL",
                            "value": "2"
                        },
                        {
                            "name": "VBC_MUX_IIS3_PORT_DO_SEL",
                            "value": "2"
                        },
                        {
                            "name": "SmartAmp Boost",
                            "value": "0"
                        },
                        {
                            "name": "DAC LRCLK Select",
                            "value": "0"
                        },
                        {
                            "name": "AO Gain AO Playback Volume",
                            "value": "4"
                        },
                        {
                            "name": "HPL Gain HPL Playback Volume",
                            "value": "12"
                        },
                        {
                            "name": "HPR Gain HPR Playback Volume",
                            "value": "12"
                        },
                        {
                            "name": "EAR Gain EAR Playback Volume",
                            "value": "12"
                        },
                        {
                            "name": "AO Mixer AOL Switch",
                            "value": "1"
                        },
                        {
                            "name": "AO Mixer AOR Switch",
                            "value": "1"
                        },
                        {
                            "name": "AOL EAR Sel",
                            "value": "1"
                        },
                        {
                            "name": "DA AOR Switch",
                            "value": "1"
                        },
                        {
                            "name": "IVSENCE_FUNC_DSP",
                            "value": "1"
                        },
                        {
                            "name": "ag_iis0_ext_sel_v2",
                            "value": "1"
                        },
                        {
                            "name": "ag_iis1_ext_sel_v2",
                            "value": "1"
                        },
                        {
                            "name": "VBC ADC0 DG Set",
                            "value": "127 127"
                        },
                        {
                            "name": "aw87xxx_profile_switch_0",
                            "value": "0"
                        }
                    ],
                    "Bluetooth_SCO_Headset": [
                        {
                            "name": "agdsp_access_en",
                            "value": "1"
                        },
                        {
                            "name": "agdsp_access_a2dp_en",
                            "value": "1"
                        },
                        {
                            "name": "VBC_IIS_RX2_WD_SEL",
                            "value": "1"
                        },
                        {
                            "name": "ag_iis0_ext_sel_v2",
                            "value": "1"
                        },
                        {
                            "name": "ag_iis1_ext_sel_v2",
                            "value": "1"
                        },
                        {
                            "name": "VBC_IIS_INF_SYS_SEL",
                            "value": "1"
                        },
                        {
                            "name": "ADC LRCLK Select",
                            "value": "1"
                        },
                        {
                            "name": "ADC1 LRCLK Select",
                            "value": "1"
                        },
                        {
                            "name": "Speaker Function",
                            "value": "1"
                        },
                        {
                            "name": "Mic Function",
                            "value": "1"
                        },
                        {
                            "name": "S_NORMAL_AP01_P_CODEC SWITCH",
                            "value": "1"
                        },
                        {
                            "name": "S_NORMAL_AP01_C_CODEC SWITCH",
                            "value": "1"
                        },
                        {
                            "name": "S_NORMAL_AP23_P_CODEC SWITCH",
                            "value": "1"
                        },
                        {
                            "name": "S_NORMAL_AP23_C_CODEC SWITCH",
                            "value": "1"
                        },
                        {
                            "name": "S_CAPTURE_DSP_CODEC SWITCH",
                            "value": "1"
                        },
                        {
                            "name": "S_FAST_P_CODEC SWITCH",
                            "value": "1"
                        },
                        {
                            "name": "S_OFFLOAD_CODEC SWITCH",
                            "value": "1"
                        },
                        {
                            "name": "S_VOICE_P_CODEC SWITCH",
                            "value": "1"
                        },
                        {
                            "name": "S_VOICE_C_CODEC SWITCH",
                            "value": "1"
                        },
                        {
                            "name": "S_VOIP_P_CODEC SWITCH",
                            "value": "1"
                        },
                        {
                            "name": "S_VOIP_C_CODEC SWITCH",
                            "value": "1"
                        },
                        {
                            "name": "S_FM_CODEC SWITCH",
                            "value": "1"
                        },
                        {
                            "name": "S_LOOP_P_CODEC SWITCH",
                            "value": "1"
                        },
                        {
                            "name": "S_LOOP_C_CODEC SWITCH",
                            "value": "1"
                        },
                        {
                            "name": "S_FM_DSP_CODEC SWITCH",
                            "value": "1"
                        },
                        {
                            "name": "S_VOICE_PCM_P SWITCH",
                            "value": "1"
                        },
                        {
                            "name": "S_FAST_P_SMART_AMP SWITCH",
                            "value": "1"
                        },
                        {
                            "name": "ADC_1 Mixer MIC1PGA_1 Switch",
                            "value": "1"
                        },
                        {
                            "name": "AUD ADC0L Switch",
                            "value": "1"
                        },
                        {
                            "name": "AUD ADC0R Switch",
                            "value": "1"
                        },
                        {
                            "name": "ADC_1 Gain ADC_1 Capture Volume",
                            "value": "6"
                        },
                        {
                            "name": "ADC_2 Gain ADC_2 Capture Volume",
                            "value": "7"
                        },
                        {
                            "name": "ADC_3 Gain ADC_3 Capture Volume",
                            "value": "6"
                        },
                        {
                            "name": "AO Gain AO Playback Volume",
                            "value": "4"
                        },
                        {
                            "name": "AO Mixer AOL Switch",
                            "value": "1"
                        },
                        {
                            "name": "AO Mixer AOR Switch",
                            "value": "1"
                        },
                        {
                            "name": "AOL EAR Sel",
                            "value": "1"
                        },
                        {
                            "name": "DA AOR Switch",
                            "value": "1"
                        },
                        {
                            "name": "HPL Gain HPL Playback Volume",
                            "value": "12"
                        },
                        {
                            "name": "HPR Gain HPR Playback Volume",
                            "value": "12"
                        },
                        {
                            "name": "EAR Gain EAR Playback Volume",
                            "value": "12"
                        },
                        {
                            "name": "ADC_3 Mixer MIC3PGA_3 Switch",
                            "value": "0"
                        },
                        {
                            "name": "Aux Mic2 Function",
                            "value": "0"
                        }
                    ]
                }
            ],
            "low-latency-communication": [
                {
                    "Speaker": [
                        {
                            "name": "agdsp_access_en",
                            "value": "1"
                        },
                        {
                            "name": "agdsp_access_a2dp_en",
                            "value": "1"
                        },
                        {
                            "name": "VBC_IIS_TX0_LRMOD_SEL",
                            "value": "1"
                        },
                        {
                            "name": "VBC_IIS_TX1_WD_SEL",
                            "value": "1"
                        },
                        {
                            "name": "DAC Gain DAC Playback Volume",
                            "value": "2"
                        },
                        {
                            "name": "Speaker Function",
                            "value": "1"
                        },
                        {
                            "name": "S_NORMAL_AP01_P_CODEC SWITCH",
                            "value": "1"
                        },
                        {
                            "name": "S_NORMAL_AP23_P_CODEC SWITCH",
                            "value": "1"
                        },
                        {
                            "name": "S_FAST_P_CODEC SWITCH",
                            "value": "1"
                        },
                        {
                            "name": "S_OFFLOAD_CODEC SWITCH",
                            "value": "1"
                        },
                        {
                            "name": "S_VOICE_P_CODEC SWITCH",
                            "value": "1"
                        },
                        {
                            "name": "S_VOIP_P_CODEC SWITCH",
                            "value": "1"
                        },
                        {
                            "name": "S_FM_CODEC SWITCH",
                            "value": "1"
                        },
                        {
                            "name": "S_LOOP_P_CODEC SWITCH",
                            "value": "1"
                        },
                        {
                            "name": "S_FM_DSP_CODEC SWITCH",
                            "value": "1"
                        },
                        {
                            "name": "S_VOICE_PCM_P SWITCH",
                            "value": "1"
                        },
                        {
                            "name": "S_FAST_P_SMART_AMP SWITCH",
                            "value": "1"
                        },
                        {
                            "name": "VBC_MUX_DAC0_IIS_PORT_SEL",
                            "value": "0"
                        },
                        {
                            "name": "VBC_MUX_DAC1_IIS_PORT_SEL",
                            "value": "0"
                        },
                        {
                            "name": "VBC_MUX_IIS0_PORT_DO_SEL",
                            "value": "0"
                        },
                        {
                            "name": "VBC_MUX_IIS2_PORT_DO_SEL",
                            "value": "2"
                        },
                        {
                            "name": "VBC_MUX_IIS3_PORT_DO_SEL",
                            "value": "2"
                        },
                        {
                            "name": "SmartAmp Boost",
                            "value": "0"
                        },
                        {
                            "name": "DAC LRCLK Select",
                            "value": "0"
                        },
                        {
                            "name": "AO Gain AO Playback Volume",
                            "value": "4"
                        },
                        {
                            "name": "HPL Gain HPL Playback Volume",
                            "value": "12"
                        },
                        {
                            "name": "HPR Gain HPR Playback Volume",
                            "value": "12"
                        },
                        {
                            "name": "EAR Gain EAR Playback Volume",
                            "value": "12"
                        },
                        {
                            "name": "AO Mixer AOL Switch",
                            "value": "1"
                        },
                        {
                            "name": "AO Mixer AOR Switch",
                            "value": "1"
                        },
                        {
                            "name": "AOL EAR Sel",
                            "value": "1"
                        },
                        {
                            "name": "DA AOR Switch",
                            "value": "1"
                        },
                        {
                            "name": "IVSENCE_FUNC_DSP",
                            "value": "1"
                        },
                        {
                            "name": "ag_iis0_ext_sel_v2",
                            "value": "1"
                        },
                        {
                            "name": "ag_iis1_ext_sel_v2",
                            "value": "1"
                        },
                        {
                            "name": "VBC ADC0 DG Set",
                            "value": "127 127"
                        },
                        {
                            "name": "aw87xxx_profile_switch_0",
                            "value": "0"
                        },
                        {
                            "name": "VBC_VOLUME",
                            "value": "0"
                        }
                    ],
                    "Headphones": [
                        {
                            "name": "agdsp_access_en",
                            "value": "1"
                        }
                    ],
                    "Mic": [
                        {
                            "name": "agdsp_access_en",
                            "value": "1"
                        },
                        {
                            "name": "agdsp_access_a2dp_en",
                            "value": "1"
                        },
                        {
                            "name": "VBC_IIS_RX2_WD_SEL",
                            "value": "1"
                        },
                        {
                            "name": "ag_iis0_ext_sel_v2",
                            "value": "1"
                        },
                        {
                            "name": "ag_iis1_ext_sel_v2",
                            "value": "1"
                        },
                        {
                            "name": "VBC_IIS_INF_SYS_SEL",
                            "value": "1"
                        },
                        {
                            "name": "ADC LRCLK Select",
                            "value": "1"
                        },
                        {
                            "name": "ADC1 LRCLK Select",
                            "value": "1"
                        },
                        {
                            "name": "Speaker Function",
                            "value": "1"
                        },
                        {
                            "name": "Mic Function",
                            "value": "1"
                        },
                        {
                            "name": "S_NORMAL_AP01_P_CODEC SWITCH",
                            "value": "1"
                        },
                        {
                            "name": "S_NORMAL_AP01_C_CODEC SWITCH",
                            "value": "1"
                        },
                        {
                            "name": "S_NORMAL_AP23_P_CODEC SWITCH",
                            "value": "1"
                        },
                        {
                            "name": "S_NORMAL_AP23_C_CODEC SWITCH",
                            "value": "1"
                        },
                        {
                            "name": "S_CAPTURE_DSP_CODEC SWITCH",
                            "value": "1"
                        },
                        {
                            "name": "S_FAST_P_CODEC SWITCH",
                            "value": "1"
                        },
                        {
                            "name": "S_OFFLOAD_CODEC SWITCH",
                            "value": "1"
                        },
                        {
                            "name": "S_VOICE_P_CODEC SWITCH",
                            "value": "1"
                        },
                        {
                            "name": "S_VOICE_C_CODEC SWITCH",
                            "value": "1"
                        },
                        {
                            "name": "S_VOIP_P_CODEC SWITCH",
                            "value": "1"
                        },
                        {
                            "name": "S_VOIP_C_CODEC SWITCH",
                            "value": "1"
                        },
                        {
                            "name": "S_FM_CODEC SWITCH",
                            "value": "1"
                        },
                        {
                            "name": "S_LOOP_P_CODEC SWITCH",
                            "value": "1"
                        },
                        {
                            "name": "S_LOOP_C_CODEC SWITCH",
                            "value": "1"
                        },
                        {
                            "name": "S_FM_DSP_CODEC SWITCH",
                            "value": "1"
                        },
                        {
                            "name": "S_VOICE_PCM_P SWITCH",
                            "value": "1"
                        },
                        {
                            "name": "S_FAST_P_SMART_AMP SWITCH",
                            "value": "1"
                        },
                        {
                            "name": "ADC_1 Mixer MIC1PGA_1 Switch",
                            "value": "1"
                        },
                        {
                            "name": "AUD ADC0L Switch",
                            "value": "1"
                        },
                        {
                            "name": "AUD ADC0R Switch",
                            "value": "1"
                        },
                        {
                            "name": "ADC_1 Gain ADC_1 Capture Volume",
                            "value": "6"
                        },
                        {
                            "name": "ADC_2 Gain ADC_2 Capture Volume",
                            "value": "7"
                        },
                        {
                            "name": "ADC_3 Gain ADC_3 Capture Volume",
                            "value": "6"
                        },
                        {
                            "name": "AO Gain AO Playback Volume",
                            "value": "4"
                        },
                        {
                            "name": "AO Mixer AOL Switch",
                            "value": "1"
                        },
                        {
                            "name": "AO Mixer AOR Switch",
                            "value": "1"
                        },
                        {
                            "name": "AOL EAR Sel",
                            "value": "1"
                        },
                        {
                            "name": "DA AOR Switch",
                            "value": "1"
                        },
                        {
                            "name": "HPL Gain HPL Playback Volume",
                            "value": "12"
                        },
                        {
                            "name": "HPR Gain HPR Playback Volume",
                            "value": "12"
                        },
                        {
                            "name": "EAR Gain EAR Playback Volume",
                            "value": "12"
                        }
                    ]
                }
            ],
            "ringtone-playback": [
                {
                    "Speaker": [
                        {
                            "name": "VBC_IIS_TX0_WD_SEL",
                            "value": "1"
                        },
                        {
                            "name": "VBC_IIS_TX1_WD_SEL",
                            "value": "1"
                        },
                        {
                            "name": "VBC_IIS_MASTER_ENALBE",
                            "value": "0"
                        },
                        {
                            "name": "VBC_IIS_MST_SEL_0_TYPE",
                            "value": "0"
                        },
                        {
                            "name": "VBC_MUX_DAC0_IIS_PORT_SEL",
                            "value": "0"
                        },
                        {
                            "name": "VBC_MUX_DAC1_IIS_PORT_SEL",
                            "value": "0"
                        },
                        {
                            "name": "VBC_MUX_IIS3_PORT_DO_SEL",
                            "value": "2"
                        },
                        {
                            "name": "VBC_MUX_MST_IIS0_PORT_DO_SEL",
                            "value": "0"
                        },
                        {
                            "name": "VBC_MUX_IIS2_PORT_DO_SEL",
                            "value": "2"
                        },
                        {
                            "name": "VBC_MUX_IIS0_PORT_DO_SEL",
                            "value": "0"
                        },
                        {
                            "name": "VBC_IIS_RX0_WD_SEL",
                            "value": "1"
                        },
                        {
                            "name": "VBC_IIS_RX1_WD_SEL",
                            "value": "1"
                        },
                        {
                            "name": "VBC_IIS_RX2_WD_SEL",
                            "value": "1"
                        },
                        {
                            "name": "VBC_MUX_ADC0_IIS_PORT_SEL",
                            "value": "1"
                        },
                        {
                            "name": "VBC_MUX_ADC1_IIS_PORT_SEL",
                            "value": "1"
                        },
                        {
                            "name": "VBC_MUX_ADC2_IIS_PORT_SEL",
                            "value": "1"
                        },
                        {
                            "name": "VBC_MUX_ADC3_IIS_PORT_SEL",
                            "value": "3"
                        },
                        {
                            "name": "VBC_SRC_BT_DAC",
                            "value": "48000"
                        },
                        {
                            "name": "VBC_SRC_BT_ADC",
                            "value": "48000"
                        },
                        {
                            "name": "VBC_VOLUME",
                            "value": "0"
                        },
                        {
                            "name": "ADC_1 Gain ADC_1 Capture Volume",
                            "value": "7"
                        },
                        {
                            "name": "ADC_2 Gain ADC_2 Capture Volume",
                            "value": "7"
                        },
                        {
                            "name": "ADC_3 Gain ADC_3 Capture Volume",
                            "value": "6"
                        },
                        {
                            "name": "DAC Gain DAC Playback Volume",
                            "value": "2"
                        },
                        {
                            "name": "ag_iis2_ext_sel_v2",
                            "value": "0"
                        },
                        {
                            "name": "VBC DAC0 DSP MDG Set",
                            "value": "0 0"
                        },
                        {
                            "name": "VBC DAC1 DSP MDG Set",
                            "value": "0 0"
                        },
                        {
                            "name": "VBC DAC0 AUD MDG Set",
                            "value": "0 0"
                        },
                        {
                            "name": "VBC DAC0 AUD23 MDG Set",
                            "value": "0 0"
                        },
                        {
                            "name": "VBC_UL_MUTE",
                            "value": "0"
                        },
                        {
                            "name": "VBC_DL_MUTE",
                            "value": "0"
                        },
                        {
                            "name": "VBC_IIS_TX0_LRMOD_SEL",
                            "value": "1"
                        },
                        {
                            "name": "VBC_IIS_RX2_LRMOD_SEL",
                            "value": "0"
                        },
                        {
                            "name": "DAC LRCLK Select",
                            "value": "0"
                        },
                        {
                            "name": "ADC LRCLK Select",
                            "value": "1"
                        },
                        {
                            "name": "ADC1 LRCLK Select",
                            "value": "1"
                        },
                        {
                            "name": "S_VOICE_P_BT SWITCH",
                            "value": "0"
                        },
                        {
                            "name": "S_VOIP_P_BT SWITCH",
                            "value": "0"
                        },
                        {
                            "name": "S_LOOP_P_BT SWITCH",
                            "value": "0"
                        },
                        {
                            "name": "S_FAST_P_BT SWITCH",
                            "value": "0"
                        },
                        {
                            "name": "S_NORMAL_AP01_P_BT SWITCH",
                            "value": "0"
                        },
                        {
                            "name": "S_CAPTURE_BT SWITCH",
                            "value": "0"
                        },
                        {
                            "name": "S_VOICE_C_BT SWITCH",
                            "value": "0"
                        },
                        {
                            "name": "S_VOIP_C_BT SWITCH",
                            "value": "0"
                        },
                        {
                            "name": "S_LOOP_C_BT SWITCH",
                            "value": "0"
                        },
                        {
                            "name": "S_BTSCO_CAP_DSP_C SWITCH",
                            "value": "0"
                        },
                        {
                            "name": "agdsp_access_en",
                            "value": "1"
                        },
                        {
                            "name": "agdsp_access_a2dp_en",
                            "value": "1"
                        },
                        {
                            "name": "VBC_IIS_TX0_LRMOD_SEL",
                            "value": "1"
                        },
                        {
                            "name": "VBC_IIS_TX1_WD_SEL",
                            "value": "1"
                        },
                        {
                            "name": "DAC Gain DAC Playback Volume",
                            "value": "2"
                        },
                        {
                            "name": "Speaker Function",
                            "value": "1"
                        },
                        {
                            "name": "S_NORMAL_AP01_P_CODEC SWITCH",
                            "value": "1"
                        },
                        {
                            "name": "S_NORMAL_AP23_P_CODEC SWITCH",
                            "value": "1"
                        },
                        {
                            "name": "S_FAST_P_CODEC SWITCH",
                            "value": "1"
                        },
                        {
                            "name": "S_OFFLOAD_CODEC SWITCH",
                            "value": "1"
                        },
                        {
                            "name": "S_VOICE_P_CODEC SWITCH",
                            "value": "1"
                        },
                        {
                            "name": "S_VOIP_P_CODEC SWITCH",
                            "value": "1"
                        },
                        {
                            "name": "S_FM_CODEC SWITCH",
                            "value": "1"
                        },
                        {
                            "name": "S_LOOP_P_CODEC SWITCH",
                            "value": "1"
                        },
                        {
                            "name": "S_FM_DSP_CODEC SWITCH",
                            "value": "1"
                        },
                        {
                            "name": "S_VOICE_PCM_P SWITCH",
                            "value": "1"
                        },
                        {
                            "name": "S_FAST_P_SMART_AMP SWITCH",
                            "value": "1"
                        },
                        {
                            "name": "VBC_MUX_DAC0_IIS_PORT_SEL",
                            "value": "0"
                        },
                        {
                            "name": "VBC_MUX_DAC1_IIS_PORT_SEL",
                            "value": "0"
                        },
                        {
                            "name": "VBC_MUX_IIS0_PORT_DO_SEL",
                            "value": "0"
                        },
                        {
                            "name": "VBC_MUX_IIS2_PORT_DO_SEL",
                            "value": "2"
                        },
                        {
                            "name": "VBC_MUX_IIS3_PORT_DO_SEL",
                            "value": "2"
                        },
                        {
                            "name": "SmartAmp Boost",
                            "value": "0"
                        },
                        {
                            "name": "DAC LRCLK Select",
                            "value": "0"
                        },
                        {
                            "name": "AO Gain AO Playback Volume",
                            "value": "4"
                        },
                        {
                            "name": "HPL Gain HPL Playback Volume",
                            "value": "12"
                        },
                        {
                            "name": "HPR Gain HPR Playback Volume",
                            "value": "12"
                        },
                        {
                            "name": "EAR Gain EAR Playback Volume",
                            "value": "12"
                        },
                        {
                            "name": "AO Mixer AOL Switch",
                            "value": "1"
                        },
                        {
                            "name": "AO Mixer AOR Switch",
                            "value": "1"
                        },
                        {
                            "name": "AOL EAR Sel",
                            "value": "1"
                        },
                        {
                            "name": "DA AOR Switch",
                            "value": "1"
                        },
                        {
                            "name": "IVSENCE_FUNC_DSP",
                            "value": "1"
                        },
                        {
                            "name": "ag_iis0_ext_sel_v2",
                            "value": "1"
                        },
                        {
                            "name": "ag_iis1_ext_sel_v2",
                            "value": "1"
                        },
                        {
                            "name": "VBC ADC0 DG Set",
                            "value": "127 127"
                        },
                        {
                            "name": "aw87xxx_profile_switch_0",
                            "value": "0"
                        }
                    ],
                    "Mic": [
                        {
                            "name": "agdsp_access_en",
                            "value": "1"
                        },
                        {
                            "name": "agdsp_access_a2dp_en",
                            "value": "1"
                        },
                        {
                            "name": "VBC_IIS_RX2_WD_SEL",
                            "value": "1"
                        },
                        {
                            "name": "ag_iis0_ext_sel_v2",
                            "value": "1"
                        },
                        {
                            "name": "ag_iis1_ext_sel_v2",
                            "value": "1"
                        },
                        {
                            "name": "VBC_IIS_INF_SYS_SEL",
                            "value": "1"
                        },
                        {
                            "name": "ADC LRCLK Select",
                            "value": "1"
                        },
                        {
                            "name": "ADC1 LRCLK Select",
                            "value": "1"
                        },
                        {
                            "name": "Speaker Function",
                            "value": "1"
                        },
                        {
                            "name": "Mic Function",
                            "value": "1"
                        },
                        {
                            "name": "S_NORMAL_AP01_P_CODEC SWITCH",
                            "value": "1"
                        },
                        {
                            "name": "S_NORMAL_AP01_C_CODEC SWITCH",
                            "value": "1"
                        },
                        {
                            "name": "S_NORMAL_AP23_P_CODEC SWITCH",
                            "value": "1"
                        },
                        {
                            "name": "S_NORMAL_AP23_C_CODEC SWITCH",
                            "value": "1"
                        },
                        {
                            "name": "S_CAPTURE_DSP_CODEC SWITCH",
                            "value": "1"
                        },
                        {
                            "name": "S_FAST_P_CODEC SWITCH",
                            "value": "1"
                        },
                        {
                            "name": "S_OFFLOAD_CODEC SWITCH",
                            "value": "1"
                        },
                        {
                            "name": "S_VOICE_P_CODEC SWITCH",
                            "value": "1"
                        },
                        {
                            "name": "S_VOICE_C_CODEC SWITCH",
                            "value": "1"
                        },
                        {
                            "name": "S_VOIP_P_CODEC SWITCH",
                            "value": "1"
                        },
                        {
                            "name": "S_VOIP_C_CODEC SWITCH",
                            "value": "1"
                        },
                        {
                            "name": "S_FM_CODEC SWITCH",
                            "value": "1"
                        },
                        {
                            "name": "S_LOOP_P_CODEC SWITCH",
                            "value": "1"
                        },
                        {
                            "name": "S_LOOP_C_CODEC SWITCH",
                            "value": "1"
                        },
                        {
                            "name": "S_FM_DSP_CODEC SWITCH",
                            "value": "1"
                        },
                        {
                            "name": "S_VOICE_PCM_P SWITCH",
                            "value": "1"
                        },
                        {
                            "name": "S_FAST_P_SMART_AMP SWITCH",
                            "value": "1"
                        },
                        {
                            "name": "ADC_1 Mixer MIC1PGA_1 Switch",
                            "value": "1"
                        },
                        {
                            "name": "AUD ADC0L Switch",
                            "value": "1"
                        },
                        {
                            "name": "AUD ADC0R Switch",
                            "value": "1"
                        },
                        {
                            "name": "ADC_1 Gain ADC_1 Capture Volume",
                            "value": "6"
                        },
                        {
                            "name": "ADC_2 Gain ADC_2 Capture Volume",
                            "value": "7"
                        },
                        {
                            "name": "ADC_3 Gain ADC_3 Capture Volume",
                            "value": "6"
                        },
                        {
                            "name": "AO Gain AO Playback Volume",
                            "value": "4"
                        },
                        {
                            "name": "AO Mixer AOL Switch",
                            "value": "1"
                        },
                        {
                            "name": "AO Mixer AOR Switch",
                            "value": "1"
                        },
                        {
                            "name": "AOL EAR Sel",
                            "value": "1"
                        },
                        {
                            "name": "DA AOR Switch",
                            "value": "1"
                        },
                        {
                            "name": "HPL Gain HPL Playback Volume",
                            "value": "12"
                        },
                        {
                            "name": "HPR Gain HPR Playback Volume",
                            "value": "12"
                        },
                        {
                            "name": "EAR Gain EAR Playback Volume",
                            "value": "12"
                        }
                    ],
                    "Bluetooth": [
                        {
                            "name": "agdsp_access_en",
                            "value": "1"
                        },
                        {
                            "name": "agdsp_access_a2dp_en",
                            "value": "1"
                        },
                        {
                            "name": "VBC_IIS_TX0_WD_SEL",
                            "value": "0"
                        },
                        {
                            "name": "VBC_IIS_TX1_WD_SEL",
                            "value": "0"
                        },
                        {
                            "name": "VBC_IIS_MASTER_ENALBE",
                            "value": "1"
                        },
                        {
                            "name": "VBC_IIS_MST_SEL_0_TYPE",
                            "value": "1"
                        },
                        {
                            "name": "VBC_MUX_DAC0_IIS_PORT_SEL",
                            "value": "0"
                        },
                        {
                            "name": "VBC_MUX_DAC1_IIS_PORT_SEL",
                            "value": "3"
                        },
                        {
                            "name": "VBC_MUX_IIS3_PORT_DO_SEL",
                            "value": "1"
                        },
                        {
                            "name": "VBC_MUX_MST_IIS0_PORT_DO_SEL",
                            "value": "0"
                        },
                        {
                            "name": "VBC_MUX_IIS2_PORT_DO_SEL",
                            "value": "2"
                        },
                        {
                            "name": "VBC_MUX_IIS0_PORT_DO_SEL",
                            "value": "2"
                        },
                        {
                            "name": "VBC_IIS_RX0_WD_SEL",
                            "value": "0"
                        },
                        {
                            "name": "VBC_IIS_RX1_WD_SEL",
                            "value": "0"
                        },
                        {
                            "name": "VBC_IIS_RX2_WD_SEL",
                            "value": "0"
                        },
                        {
                            "name": "VBC_MUX_ADC0_IIS_PORT_SEL",
                            "value": "3"
                        },
                        {
                            "name": "VBC_MUX_ADC1_IIS_PORT_SEL",
                            "value": "3"
                        },
                        {
                            "name": "VBC_MUX_ADC2_IIS_PORT_SEL",
                            "value": "3"
                        },
                        {
                            "name": "VBC_MUX_ADC3_IIS_PORT_SEL",
                            "value": "3"
                        },
                        {
                            "name": "VBC_SRC_BT_DAC",
                            "value": "8000"
                        },
                        {
                            "name": "VBC_SRC_BT_ADC",
                            "value": "8000"
                        },
                        {
                            "name": "VBC_VOLUME",
                            "value": "8"
                        },
                        {
                            "name": "DAC Gain DAC Playback Volume",
                            "value": "0"
                        },
                        {
                            "name": "ag_iis1_ext_sel_v2",
                            "value": "1"
                        },
                        {
                            "name": "ag_iis2_ext_sel_v2",
                            "value": "0"
                        },
                        {
                            "name": "SYS_IIS0",
                            "value": "3"
                        },
                        {
                            "name": "VBC_DL_MUTE",
                            "value": "0"
                        },
                        {
                            "name": "VBC_IIS_TX0_LRMOD_SEL",
                            "value": "0"
                        },
                        {
                            "name": "VBC_IIS_RX2_LRMOD_SEL",
                            "value": "0"
                        },
                        {
                            "name": "DAC LRCLK Select",
                            "value": "0"
                        },
                        {
                            "name": "ADC LRCLK Select",
                            "value": "0"
                        },
                        {
                            "name": "ADC1 LRCLK Select",
                            "value": "0"
                        },
                        {
                            "name": "S_VOICE_P_BT SWITCH",
                            "value": "1"
                        },
                        {
                            "name": "S_VOIP_P_BT SWITCH",
                            "value": "1"
                        },
                        {
                            "name": "S_LOOP_P_BT SWITCH",
                            "value": "1"
                        },
                        {
                            "name": "S_FAST_P_BT SWITCH",
                            "value": "1"
                        },
                        {
                            "name": "S_NORMAL_AP01_P_BT SWITCH",
                            "value": "1"
                        },
                        {
                            "name": "S_CAPTURE_BT SWITCH",
                            "value": "1"
                        },
                        {
                            "name": "S_VOICE_PCM_P SWITCH",
                            "value": "1"
                        },
                        {
                            "name": "S_FAST_P_SMART_AMP SWITCH",
                            "value": "1"
                        },
                        {
                            "name": "S_VOICE_C_BT SWITCH",
                            "value": "1"
                        },
                        {
                            "name": "S_VOIP_C_BT SWITCH",
                            "value": "1"
                        },
                        {
                            "name": "S_LOOP_C_BT SWITCH",
                            "value": "1"
                        },
                        {
                            "name": "S_BTSCO_CAP_DSP_C SWITCH",
                            "value": "1"
                        }
                    ]
                }
            ],
            "voice-call": [
                {
                    "Speaker": [
                        {
                            "name": "VBC DAC0 DSP MDG Set",
                            "value": "0 1024"
                        },
                        {
                            "name": "VBC DAC1 DSP MDG Set",
                            "value": "0 1024"
                        },
                        {
                            "name": "VBC DAC0 AUD MDG Set",
                            "value": "0 1024"
                        },
                        {
                            "name": "VBC DAC0 AUD23 MDG Set",
                            "value": "0 1024"
                        },
                        {
                            "name": "VBC DAC1 DG Set",
                            "value": "24 24"
                        },
                        {
                            "name": "VBC ADC2 DG Set",
                            "value": "24 24"
                        },
                        {
                            "name": "VBC ADC3 DG Set",
                            "value": "24 24"
                        },
                        {
                            "name": "VBC ST DG Set",
                            "value": "24 24"
                        },
                        {
                            "name": "VBC_MUX_ADC3",
                            "value": "5"
                        },
                        {
                            "name": "VBC_MUX_ST",
                            "value": "4"
                        },
                        {
                            "name": "VBC_MUX_ADC1_IIS_PORT_SEL",
                            "value": "2"
                        },
                        {
                            "name": "VBC_MUX_ADC3_IIS_PORT_SEL",
                            "value": "0"
                        },
                        {
                            "name": "agdsp_access_en",
                            "value": "1"
                        },
                        {
                            "name": "agdsp_access_a2dp_en",
                            "value": "1"
                        },
                        {
                            "name": "VBC_VOLUME",
                            "value": "3"
                        },
                        {
                            "name": "Audio Structure Profile Select",
                            "value": "168427525"
                        },
                        {
                            "name": "DSP VBC Profile Select",
                            "value": "168427525"
                        },
                        {
                            "name": "NXP Profile Select",
                            "value": "168427525"
                        },
                        {
                            "name": "VBC_IIS_RX2_WD_SEL",
                            "value": "1"
                        },
                        {
                            "name": "VBC_IIS_TX0_LRMOD_SEL",
                            "value": "1"
                        },
                        {
                            "name": "ag_iis0_ext_sel_v2",
                            "value": "1"
                        },
                        {
                            "name": "ag_iis1_ext_sel_v2",
                            "value": "1"
                        },
                        {
                            "name": "DAC LRCLK Select",
                            "value": "1"
                        },
                        {
                            "name": "ADC LRCLK Select",
                            "value": "1"
                        },
                        {
                            "name": "ADC1 LRCLK Select",
                            "value": "1"
                        },
                        {
                            "name": "DAHP OS D",
                            "value": "5"
                        },
                        {
                            "name": "ADD0 DATA SEL",
                            "value": "1"
                        },
                        {
                            "name": "Speaker Function",
                            "value": "1"
                        },
                        {
                            "name": "Speaker1 Function",
                            "value": "1"
                        },
                        {
                            "name": "Mic Function",
                            "value": "1"
                        },
                        {
                            "name": "S_NORMAL_AP01_P_CODEC SWITCH",
                            "value": "1"
                        },
                        {
                            "name": "S_NORMAL_AP01_C_CODEC SWITCH",
                            "value": "1"
                        },
                        {
                            "name": "S_NORMAL_AP23_P_CODEC SWITCH",
                            "value": "1"
                        },
                        {
                            "name": "S_NORMAL_AP23_C_CODEC SWITCH",
                            "value": "1"
                        },
                        {
                            "name": "S_CAPTURE_DSP_CODEC SWITCH",
                            "value": "1"
                        },
                        {
                            "name": "S_FAST_P_CODEC SWITCH",
                            "value": "1"
                        },
                        {
                            "name": "S_OFFLOAD_CODEC SWITCH",
                            "value": "1"
                        },
                        {
                            "name": "S_VOICE_P_CODEC SWITCH",
                            "value": "1"
                        },
                        {
                            "name": "S_VOICE_C_CODEC SWITCH",
                            "value": "1"
                        },
                        {
                            "name": "S_VOIP_P_CODEC SWITCH",
                            "value": "1"
                        },
                        {
                            "name": "S_VOIP_C_CODEC SWITCH",
                            "value": "1"
                        },
                        {
                            "name": "S_FM_CODEC SWITCH",
                            "value": "1"
                        },
                        {
                            "name": "S_LOOP_P_CODEC SWITCH",
                            "value": "1"
                        },
                        {
                            "name": "S_LOOP_C_CODEC SWITCH",
                            "value": "1"
                        },
                        {
                            "name": "S_FM_DSP_CODEC SWITCH",
                            "value": "1"
                        },
                        {
                            "name": "S_VOICE_CAP_C SWITCH",
                            "value": "1"
                        },
                        {
                            "name": "S_VOICE_PCM_P SWITCH",
                            "value": "1"
                        },
                        {
                            "name": "S_FAST_P_SMART_AMP SWITCH",
                            "value": "1"
                        },
                        {
                            "name": "ADC_1 Mixer MIC1PGA_1 Switch",
                            "value": "1"
                        },
                        {
                            "name": "AUD ADC0L Switch",
                            "value": "1"
                        },
                        {
                            "name": "AUD ADC0R Switch",
                            "value": "1"
                        },
                        {
                            "name": "ADC_1 Gain ADC_1 Capture Volume",
                            "value": "6"
                        },
                        {
                            "name": "ADC_2 Gain ADC_2 Capture Volume",
                            "value": "6"
                        },
                        {
                            "name": "ADC_3 Gain ADC_3 Capture Volume",
                            "value": "6"
                        },
                        {
                            "name": "HPL Mixer DACLHPL Switch",
                            "value": "1"
                        },
                        {
                            "name": "HPR Mixer DACRHPR Switch",
                            "value": "1"
                        },
                        {
                            "name": "HP Virt Switch",
                            "value": "1"
                        },
                        {
                            "name": "EAR Gain EAR Playback Volume",
                            "value": "2"
                        },
                        {
                            "name": "HPL EAR Sel",
                            "value": "1"
                        },
                        {
                            "name": "ADC_3 Mixer MIC3PGA_3 Switch",
                            "value": "1"
                        },
                        {
                            "name": "Aux Mic2 Function",
                            "value": "1"
                        }
                    ],
                    "Earpiece": [
                        {
                            "name": "VBC DAC1 DG Set",
                            "value": "24 24"
                        },
                        {
                            "name": "VBC ADC2 DG Set",
                            "value": "24 24"
                        },
                        {
                            "name": "VBC ADC3 DG Set",
                            "value": "24 24"
                        },
                        {
                            "name": "VBC ST DG Set",
                            "value": "24 24"
                        },
                        {
                            "name": "VBC_MIXER1_DAC0",
                            "value": "2"
                        },
                        {
                            "name": "VBC_MUX_ADC3",
                            "value": "5"
                        },
                        {
                            "name": "VBC_MUX_ST",
                            "value": "4"
                        },
                        {
                            "name": "VBC_MUX_ADC1_IIS_PORT_SEL",
                            "value": "2"
                        },
                        {
                            "name": "VBC_MUX_ADC3_IIS_PORT_SEL",
                            "value": "0"
                        },
                        {
                            "name": "agdsp_access_en",
                            "value": "1"
                        },
                        {
                            "name": "agdsp_access_a2dp_en",
                            "value": "1"
                        },
                        {
                            "name": "VBC_VOLUME",
                            "value": "7"
                        },
                        {
                            "name": "Audio Structure Profile Select",
                            "value": "33685509"
                        },
                        {
                            "name": "DSP VBC Profile Select",
                            "value": "33685509"
                        },
                        {
                            "name": "NXP Profile Select",
                            "value": "33685509"
                        },
                        {
                            "name": "VBC_IIS_RX2_WD_SEL",
                            "value": "1"
                        },
                        {
                            "name": "VBC_IIS_TX0_LRMOD_SEL",
                            "value": "1"
                        },
                        {
                            "name": "ag_iis0_ext_sel_v2",
                            "value": "1"
                        },
                        {
                            "name": "ag_iis0_ext_sel_v2",
                            "value": "1"
                        },
                        {
                            "name": "ADC LRCLK Select",
                            "value": "1"
                        },
                        {
                            "name": "ADC1 LRCLK Select",
                            "value": "1"
                        },
                        {
                            "name": "DAHP OS D",
                            "value": "5"
                        },
                        {
                            "name": "ADD0 DATA SEL",
                            "value": "1"
                        },
                        {
                            "name": "Earpiece Function",
                            "value": "1"
                        },
                        {
                            "name": "Mic Function",
                            "value": "1"
                        },
                        {
                            "name": "S_NORMAL_AP01_P_CODEC SWITCH",
                            "value": "1"
                        },
                        {
                            "name": "S_NORMAL_AP01_C_CODEC SWITCH",
                            "value": "1"
                        },
                        {
                            "name": "S_NORMAL_AP23_P_CODEC SWITCH",
                            "value": "1"
                        },
                        {
                            "name": "S_NORMAL_AP23_C_CODEC SWITCH",
                            "value": "1"
                        },
                        {
                            "name": "S_CAPTURE_DSP_CODEC SWITCH",
                            "value": "1"
                        },
                        {
                            "name": "S_FAST_P_CODEC SWITCH",
                            "value": "1"
                        },
                        {
                            "name": "S_OFFLOAD_CODEC SWITCH",
                            "value": "1"
                        },
                        {
                            "name": "S_VOICE_P_CODEC SWITCH",
                            "value": "1"
                        },
                        {
                            "name": "S_VOICE_C_CODEC SWITCH",
                            "value": "1"
                        },
                        {
                            "name": "S_VOIP_P_CODEC SWITCH",
                            "value": "1"
                        },
                        {
                            "name": "S_VOIP_C_CODEC SWITCH",
                            "value": "1"
                        },
                        {
                            "name": "S_FM_CODEC SWITCH",
                            "value": "1"
                        },
                        {
                            "name": "S_LOOP_P_CODEC SWITCH",
                            "value": "1"
                        },
                        {
                            "name": "S_LOOP_C_CODEC SWITCH",
                            "value": "1"
                        },
                        {
                            "name": "S_FM_DSP_CODEC SWITCH",
                            "value": "1"
                        },
                        {
                            "name": "S_VOICE_CAP_C SWITCH",
                            "value": "1"
                        },
                        {
                            "name": "S_VOICE_PCM_P SWITCH",
                            "value": "1"
                        },
                        {
                            "name": "S_FAST_P_SMART_AMP SWITCH",
                            "value": "1"
                        },
                        {
                            "name": "AUD ADC0L Switch",
                            "value": "1"
                        },
                        {
                            "name": "AUD ADC0R Switch",
                            "value": "1"
                        },
                        {
                            "name": "ADC_1 Gain ADC_1 Capture Volume",
                            "value": "1"
                        },
                        {
                            "name": "ADC_2 Gain ADC_2 Capture Volume",
                            "value": "1"
                        },
                        {
                            "name": "ADC_3 Gain ADC_3 Capture Volume",
                            "value": "1"
                        },
                        {
                            "name": "EAR Gain EAR Playback Volume",
                            "value": "2"
                        },
                        {
                            "name": "EAR_HPL Mixer DACHPL Switch",
                            "value": "1"
                        },
                        {
                            "name": "ADC_3 Mixer MIC3PGA_3 Switch",
                            "value": "1"
                        },
                        {
                            "name": "Aux Mic2 Function",
                            "value": "1"
                        }
                    ],
                    "Bluetooth": [
                        {
                            "name": "agdsp_access_en",
                            "value": "1"
                        },
                        {
                            "name": "agdsp_access_a2dp_en",
                            "value": "1"
                        },
                        {
                            "name": "VBC_IIS_TX0_WD_SEL",
                            "value": "0"
                        },
                        {
                            "name": "VBC_IIS_TX1_WD_SEL",
                            "value": "0"
                        },
                        {
                            "name": "VBC_IIS_MASTER_ENALBE",
                            "value": "1"
                        },
                        {
                            "name": "VBC_IIS_MST_SEL_0_TYPE",
                            "value": "1"
                        },
                        {
                            "name": "VBC_MUX_DAC0_IIS_PORT_SEL",
                            "value": "0"
                        },
                        {
                            "name": "VBC_MUX_DAC1_IIS_PORT_SEL",
                            "value": "3"
                        },
                        {
                            "name": "VBC_MUX_IIS3_PORT_DO_SEL",
                            "value": "1"
                        },
                        {
                            "name": "VBC_MUX_MST_IIS0_PORT_DO_SEL",
                            "value": "0"
                        },
                        {
                            "name": "VBC_MUX_IIS2_PORT_DO_SEL",
                            "value": "2"
                        },
                        {
                            "name": "VBC_MUX_IIS0_PORT_DO_SEL",
                            "value": "2"
                        },
                        {
                            "name": "VBC_IIS_RX0_WD_SEL",
                            "value": "0"
                        },
                        {
                            "name": "VBC_IIS_RX1_WD_SEL",
                            "value": "0"
                        },
                        {
                            "name": "VBC_IIS_RX2_WD_SEL",
                            "value": "0"
                        },
                        {
                            "name": "VBC_MUX_ADC0_IIS_PORT_SEL",
                            "value": "3"
                        },
                        {
                            "name": "VBC_MUX_ADC1_IIS_PORT_SEL",
                            "value": "3"
                        },
                        {
                            "name": "VBC_MUX_ADC2_IIS_PORT_SEL",
                            "value": "3"
                        },
                        {
                            "name": "VBC_MUX_ADC3_IIS_PORT_SEL",
                            "value": "3"
                        },
                        {
                            "name": "VBC_SRC_BT_DAC",
                            "value": "8000"
                        },
                        {
                            "name": "VBC_SRC_BT_ADC",
                            "value": "8000"
                        },
                        {
                            "name": "VBC_VOLUME",
                            "value": "8"
                        },
                        {
                            "name": "DAC Gain DAC Playback Volume",
                            "value": "0"
                        },
                        {
                            "name": "ag_iis1_ext_sel_v2",
                            "value": "1"
                        },
                        {
                            "name": "ag_iis2_ext_sel_v2",
                            "value": "0"
                        },
                        {
                            "name": "SYS_IIS0",
                            "value": "3"
                        },
                        {
                            "name": "VBC_DL_MUTE",
                            "value": "0"
                        },
                        {
                            "name": "VBC_IIS_TX0_LRMOD_SEL",
                            "value": "0"
                        },
                        {
                            "name": "VBC_IIS_RX2_LRMOD_SEL",
                            "value": "0"
                        },
                        {
                            "name": "DAC LRCLK Select",
                            "value": "0"
                        },
                        {
                            "name": "ADC LRCLK Select",
                            "value": "0"
                        },
                        {
                            "name": "ADC1 LRCLK Select",
                            "value": "0"
                        },
                        {
                            "name": "S_VOICE_P_BT SWITCH",
                            "value": "1"
                        },
                        {
                            "name": "S_VOIP_P_BT SWITCH",
                            "value": "1"
                        },
                        {
                            "name": "S_LOOP_P_BT SWITCH",
                            "value": "1"
                        },
                        {
                            "name": "S_FAST_P_BT SWITCH",
                            "value": "1"
                        },
                        {
                            "name": "S_NORMAL_AP01_P_BT SWITCH",
                            "value": "1"
                        },
                        {
                            "name": "S_CAPTURE_BT SWITCH",
                            "value": "1"
                        },
                        {
                            "name": "S_VOICE_PCM_P SWITCH",
                            "value": "1"
                        },
                        {
                            "name": "S_FAST_P_SMART_AMP SWITCH",
                            "value": "1"
                        },
                        {
                            "name": "S_VOICE_C_BT SWITCH",
                            "value": "1"
                        },
                        {
                            "name": "S_VOIP_C_BT SWITCH",
                            "value": "1"
                        },
                        {
                            "name": "S_LOOP_C_BT SWITCH",
                            "value": "1"
                        },
                        {
                            "name": "S_BTSCO_CAP_DSP_C SWITCH",
                            "value": "1"
                        }
                    ],
                    "Mic": [
                        {
                            "name": "ADC_3 Mixer MIC3PGA_3 Switch",
                            "value": "1"
                        },
                        {
                            "name": "Aux Mic2 Function",
                            "value": "1"
                        }
                    ],
                    "Bluetooth_SCO_Headset": [
                        {
                            "name": "agdsp_access_en",
                            "value": "1"
                        }
                    ]
                }
            ],
            "low-latency-noirq-playback": [
                {
                    "Speaker": [
                        {
                            "name": "agdsp_access_en",
                            "value": "1"
                        },
                        {
                            "name": "agdsp_access_a2dp_en",
                            "value": "1"
                        },
                        {
                            "name": "VBC_IIS_TX0_LRMOD_SEL",
                            "value": "1"
                        },
                        {
                            "name": "VBC_IIS_TX1_WD_SEL",
                            "value": "1"
                        },
                        {
                            "name": "DAC Gain DAC Playback Volume",
                            "value": "2"
                        },
                        {
                            "name": "Speaker Function",
                            "value": "1"
                        },
                        {
                            "name": "S_NORMAL_AP01_P_CODEC SWITCH",
                            "value": "1"
                        },
                        {
                            "name": "S_NORMAL_AP23_P_CODEC SWITCH",
                            "value": "1"
                        },
                        {
                            "name": "S_FAST_P_CODEC SWITCH",
                            "value": "1"
                        },
                        {
                            "name": "S_OFFLOAD_CODEC SWITCH",
                            "value": "1"
                        },
                        {
                            "name": "S_VOICE_P_CODEC SWITCH",
                            "value": "1"
                        },
                        {
                            "name": "S_VOIP_P_CODEC SWITCH",
                            "value": "1"
                        },
                        {
                            "name": "S_FM_CODEC SWITCH",
                            "value": "1"
                        },
                        {
                            "name": "S_LOOP_P_CODEC SWITCH",
                            "value": "1"
                        },
                        {
                            "name": "S_FM_DSP_CODEC SWITCH",
                            "value": "1"
                        },
                        {
                            "name": "S_VOICE_PCM_P SWITCH",
                            "value": "1"
                        },
                        {
                            "name": "S_FAST_P_SMART_AMP SWITCH",
                            "value": "1"
                        },
                        {
                            "name": "VBC_MUX_DAC0_IIS_PORT_SEL",
                            "value": "0"
                        },
                        {
                            "name": "VBC_MUX_DAC1_IIS_PORT_SEL",
                            "value": "0"
                        },
                        {
                            "name": "VBC_MUX_IIS0_PORT_DO_SEL",
                            "value": "0"
                        },
                        {
                            "name": "VBC_MUX_IIS2_PORT_DO_SEL",
                            "value": "2"
                        },
                        {
                            "name": "VBC_MUX_IIS3_PORT_DO_SEL",
                            "value": "2"
                        },
                        {
                            "name": "SmartAmp Boost",
                            "value": "0"
                        },
                        {
                            "name": "DAC LRCLK Select",
                            "value": "0"
                        },
                        {
                            "name": "AO Gain AO Playback Volume",
                            "value": "4"
                        },
                        {
                            "name": "HPL Gain HPL Playback Volume",
                            "value": "12"
                        },
                        {
                            "name": "HPR Gain HPR Playback Volume",
                            "value": "12"
                        },
                        {
                            "name": "EAR Gain EAR Playback Volume",
                            "value": "12"
                        },
                        {
                            "name": "AO Mixer AOL Switch",
                            "value": "1"
                        },
                        {
                            "name": "AO Mixer AOR Switch",
                            "value": "1"
                        },
                        {
                            "name": "AOL EAR Sel",
                            "value": "1"
                        },
                        {
                            "name": "DA AOR Switch",
                            "value": "1"
                        },
                        {
                            "name": "IVSENCE_FUNC_DSP",
                            "value": "1"
                        },
                        {
                            "name": "ag_iis0_ext_sel_v2",
                            "value": "1"
                        },
                        {
                            "name": "ag_iis1_ext_sel_v2",
                            "value": "1"
                        },
                        {
                            "name": "VBC ADC0 DG Set",
                            "value": "127 127"
                        },
                        {
                            "name": "aw87xxx_profile_switch_0",
                            "value": "0"
                        },
                        {
                            "name": "VBC_VOLUME",
                            "value": "0"
                        }
                    ],
                    "Headphones": [
                        {
                            "name": "agdsp_access_en",
                            "value": "1"
                        }
                    ]
                }
            ]
        }
    ]
}
